ntab/__init__.py
ntab/demo.py
ntab/ez.py
ntab/fmt.py
ntab/fn.py
ntab/groupby.py
ntab/html.py
ntab/nplib.py
ntab/tab.py
ntab/lib/__init__.py
ntab/lib/text.py
ntab/lib/test/test_text.py
ntab/test/test_arr_obj.py
ntab/test/test_arrs.py
ntab/test/test_basic.py
ntab/test/test_ez.py
ntab/test/test_fn.py
ntab/test/test_groupby.py
ntab/test/test_row.py
ntab-0.3.2.dist-info/DESCRIPTION.rst
ntab-0.3.2.dist-info/METADATA
ntab-0.3.2.dist-info/RECORD
ntab-0.3.2.dist-info/WHEEL
ntab-0.3.2.dist-info/metadata.json
ntab-0.3.2.dist-info/top_level.txt
