Metadata-Version: 2.0
Name: ntab
Version: 0.3.2
Summary: Simple numerical tables
Home-page: https://github.com/alexhsamuel/ntab
Author: Alex Samuel
Author-email: alex@alexsamuel.net
License: MIT
Keywords: data,table,numerical,numpy
Platform: UNKNOWN
Classifier: Development Status :: 4 - Beta
Classifier: Intended Audience :: Developers
Classifier: License :: OSI Approved :: MIT License
Classifier: Programming Language :: Python :: 3
Classifier: Programming Language :: Python :: 3.6
Requires-Dist: numpy
